goon_parser/__init__.py
goon_parser/cli.py
goon_parser/constants.py
goon_parser/error.log
goon_parser/logger.py
goon_parser/parser.py
goon_parser/test.json
goon_parser/test.txt
goon_parser/test.yaml
goon_parser/util.py
goon_parser-0.2.0.dist-info/entry_points.txt
goon_parser-0.2.0.dist-info/WHEEL
goon_parser-0.2.0.dist-info/METADATA
goon_parser-0.2.0.dist-info/RECORD
