Metadata-Version: 2.1
Name: goon-parser
Version: 0.2.0
Summary: A python package used to parse ss13 dm files into json
Author: Kyle Oliver
Author-email: 56kyleoliver@gmail.com
Requires-Python: >=3.10,<4.0
Classifier: Programming Language :: Python :: 3
Classifier: Programming Language :: Python :: 3.10
Requires-Dist: click (>=8.1.2,<9.0.0)
